script_for_create_standings/__init__.py
script_for_create_standings/racer.py
script_for_create_standings/racer_time.py
script_for_create_standings-1.1.dist-info/METADATA
script_for_create_standings-1.1.dist-info/WHEEL
script_for_create_standings-1.1.dist-info/top_level.txt
script_for_create_standings-1.1.dist-info/RECORD
