Metadata-Version: 2.1
Name: script-for-create-standings
Version: 1.1
Summary: UNKNOWN
Home-page: UNKNOWN
Author-email: dimapyatetsky@gmail.com
License: UNKNOWN
Platform: UNKNOWN
